CMakeLists.txt
LICENSE
MANIFEST.in
README.md
dev-requirements.txt
pyproject.toml
setup.py
tests/__init__.py
tests/conftest.py
tests/test_patch_lang.py
tests/test_tourniquet.py
tourniquet/__init__.py
tourniquet/error.py
tourniquet/location.py
tourniquet/models.py
tourniquet/patch_lang.py
tourniquet/target.py
tourniquet/tourniquet.py
tourniquet/version.py
tourniquet.egg-info/PKG-INFO
tourniquet.egg-info/SOURCES.txt
tourniquet.egg-info/dependency_links.txt
tourniquet.egg-info/requires.txt
tourniquet.egg-info/top_level.txt
transformer/ASTExporter.cpp
transformer/ASTExporter.h
transformer/ASTPatch.h
transformer/extractor.cpp