Metadata-Version: 2.1
Name: tourniquet
Version: 0.0.4
Summary: Syntax Guided Repair/Transformation Package
Home-page: https://github.com/trailofbits/tourniquet
Author: Carson Harmon
Author-email: carson.harmon@trailofbits.com
License: Apache-2.0
Project-URL: Documentation, https://trailofbits.github.io/tourniquet/
Platform: UNKNOWN
Classifier: Programming Language :: Python :: 3
Classifier: License :: OSI Approved :: Apache Software License
Classifier: Development Status :: 3 - Alpha
Classifier: Intended Audience :: Science/Research
Classifier: Topic :: Software Development :: Code Generators
Requires-Python: >=3.7
Provides-Extra: dev
